[
    {
        "Region": "Tatra",
        "MountainName": "Giewont",
        "info": {
            "sub_region": "Western Tatras",
            "msl": 1894,
            "country": "Poland"
        }
    },
    {
        "Region": "Tatra",
        "MountainName": "Kasprowy Wierch",
        "info": {
            "sub_region": "Western Tatras",
            "msl": 1987,
            "country": "Poland"
        }
    },
    {
        "Region": "Tatra",
        "MountainName": "Krzesanica",
        "info": {
            "sub_region": "Western Tatras",
            "msl": 2122,
            "country": "Poland"
        }
    },
    {
        "Region": "Tatra",
        "MountainName": "Jalovecky prislop",
        "info": {
            "sub_region": "Western Tatras",
            "msl": 2142,
            "country": "Slovakia"
        }
    },
    {
        "Region": "Tatra",
        "MountainName": "Kamienista",
        "info": {
            "sub_region": "Western Tatras",
            "msl": 2126,
            "country": "Slovakia/Poland"
        }
    },
    {
        "Region": "Tatra",
        "MountainName": "Starorobocianski Wierch",
        "info": {
            "sub_region": "Western Tatras",
            "msl": 2176,
            "country": "Slovakia/Poland"
        }
    },
    {
        "Region": "Tatra",
        "MountainName": "Baranec",
        "info": {
            "sub_region": "Western Tatras",
            "msl": 2184,
            "country": "Slovakia"
        }
    },
    {
        "Region": "Tatra",
        "MountainName": "Bystra",
        "info": {
            "sub_region": "Western Tatras",
            "msl": 2248,
            "country": "Slovakia"
        }
    },
    {
        "Region": "Tatra",
        "MountainName": "Jakubina",
        "info": {
            "sub_region": "Western Tatras",
            "msl": 2194,
            "country": "Slovakia"
        }
    },
    {
        "Region": "Tatra",
        "MountainName": "Gerlachovsky stit",
        "info": {
            "sub_region": "Eastern Tatras",
            "msl": 2655,
            "country": "Slovakia"
        }
    },
    {
        "Region": "Tatra",
        "MountainName": "Lomnicky stit",
        "info": {
            "sub_region": "Eastern Tatras",
            "msl": 2634,
            "country": "Slovakia"
        }
    },
    {
        "Region": "Tatra",
        "MountainName": "Ladovy stit",
        "info": {
            "sub_region": "Eastern Tatras",
            "msl": 2627,
            "country": "Slovakia"
        }
    },
    {
        "Region": "Tatra",
        "MountainName": "Zadny Gerlach",
        "info": {
            "sub_region": "Eastern Tatras",
            "msl": 2616,
            "country": "Slovakia"
        }
    },
    {
        "Region": "Tatra",
        "MountainName": "Lavinowy stit",
        "info": {
            "sub_region": "Eastern Tatras",
            "msl": 2606,
            "country": "Slovakia"
        }
    },
    {
        "Region": "Tatra",
        "MountainName": "Maly Pysny stit",
        "info": {
            "sub_region": "Eastern Tatras",
            "msl": 2592,
            "country": "Slovakia"
        }
    },
    {
        "Region": "Tatra",
        "MountainName": "Vysoka",
        "info": {
            "sub_region": "Eastern Tatras",
            "msl": 2547,
            "country": "Slovakia"
        }
    },
    {
        "Region": "Tatra",
        "MountainName": "Kezmarsky stit",
        "info": {
            "sub_region": "Eastern Tatras",
            "msl": 2558,
            "country": "Slovakia"
        }
    },
    {
        "Region": "Tatra",
        "MountainName": "Baranie rohy",
        "info": {
            "sub_region": "Eastern Tatras",
            "msl": 2626,
            "country": "Slovakia"
        }
    },
    {
        "Region": "Tatra",
        "MountainName": "Tazky stit",
        "info": {
            "sub_region": "Eastern Tatras",
            "msl": 2520,
            "country": "Slovakia"
        }
    },
    {
        "Region": "Tatra",
        "MountainName": "Rysy",
        "info": {
            "sub_region": "Eastern Tatras",
            "msl": 2499,
            "country": "Slovakia/Poland"
        }
    },
    {
        "Region": "Tatra",
        "MountainName": "Slavkovsky stit",
        "info": {
            "sub_region": "Eastern Tatras",
            "msl": 2452,
            "country": "Slovakia"
        }
    },
    {
        "Region": "Tatra",
        "MountainName": "Batizovsky stit",
        "info": {
            "sub_region": "Eastern Tatras",
            "msl": 2448,
            "country": "Slovakia"
        }
    },
    {
        "Region": "Tatra",
        "MountainName": "Jahnaci stit",
        "info": {
            "sub_region": "Eastern Tatras",
            "msl": 2230,
            "country": "Slovakia"
        }
    },
    {
        "Region": "Tatra",
        "MountainName": "Mieguszowiecki Szczyt Wielki",
        "info": {
            "sub_region": "Eastern Tatras",
            "msl": 2438,
            "country": "Slovakia/Poland"
        }
    },
    {
        "Region": "Tatra",
        "MountainName": "Niznie Rysy",
        "info": {
            "sub_region": "Eastern Tatras",
            "msl": 2430,
            "country": "Slovakia/Poland"
        }
    },
    {
        "Region": "Tatra",
        "MountainName": "Cubryna",
        "info": {
            "sub_region": "Eastern Tatras",
            "msl": 2376,
            "country": "Slovakia/Poland"
        }
    },
    {
        "Region": "Tatra",
        "MountainName": "Swinica",
        "info": {
            "sub_region": "Eastern Tatras",
            "msl": 2301,
            "country": "Slovakia/Poland"
        }
    },
    {
        "Region": "Tatra",
        "MountainName": "Kozi Wierch",
        "info": {
            "sub_region": "Eastern Tatras",
            "msl": 2291,
            "country": "Poland"
        }
    },
    {
        "Region": "Tatra",
        "MountainName": "Zamarla Turnia",
        "info": {
            "sub_region": "Eastern Tatras",
            "msl": 2179,
            "country": "Poland"
        }
    },
    {
        "Region": "Tatra",
        "MountainName": "Koscielec",
        "info": {
            "sub_region": "Eastern Tatras",
            "msl": 2155,
            "country": "Poland"
        }
    },     {
        "Region": "Tatra",
        "MountainName": "Mnich",
        "info": {
            "sub_region": "Eastern Tatras",
            "msl": 2068,
            "country": "Poland"
        }
    },   
    {
        "Region": "Beskid",
        "MountainName": "Turbacz",
        "info": {
            "sub_region": "Western Beskids",
            "msl": 1315,
            "country": "Poland"
        }
    },
    {
        "Region": "Beskid",
        "MountainName": "Pieniny",
        "info": {
            "sub_region": "Western Beskids",
            "msl": 1050,
            "country": "Poland"
        }
    },
    {
        "Region": "Beskid",
        "MountainName": "Mogielnica",
        "info": {
            "sub_region": "Western Beskids",
            "msl": 1170,
            "country": "Poland"
        }
    },
    {
        "Region": "Beskid",
        "MountainName": "Radziejowa",
        "info": {
            "sub_region": "Western Beskids",
            "msl": 1266,
            "country": "Poland"
        }
    },
    {
        "Region": "Beskid",
        "MountainName": "Busov",
        "info": {
            "sub_region": "Eastern Beskids",
            "msl": 1002,
            "country": "Slovakia"
        }
    },
    {
        "Region": "Beskid",
        "MountainName": "Stebnicka Magura",
        "info": {
            "sub_region": "Eastern Beskids",
            "msl": 900,
            "country": "Slovakia"
        }
    },
    {
        "Region": "Beskid",
        "MountainName": "Howerla",
        "info": {
            "sub_region": "Southern Beskids",
            "msl": 2061,
            "country": "Ukraine"
        }
    },
    {
        "Region": "Beskid",
        "MountainName": "Brebeneskul",
        "info": {
            "sub_region": "Southern Beskids",
            "msl": 2022,
            "country": "Ukraine"
        }
    },
    {
        "Region": "Beskid",
        "MountainName": "Pop Iwan",
        "info": {
            "sub_region": "Southern Beskids",
            "msl": 2020,
            "country": "Ukraine"
        }
    }
]
